<annotation>
	<folder>40</folder>
	<filename>FILE190712-091517F.shrink.mp4.thumb0013.jpg</filename>
	<path>/home/mi/Current/Data/Road_signs/40/FILE190712-091517F.shrink.mp4.thumb0013.jpg</path>
	<source>
		<database>Unknown</database>
	</source>
	<size>
		<width>1280</width>
		<height>720</height>
		<depth>3</depth>
	</size>
	<segmented>0</segmented>
	<object>
		<name>speed_limit_40</name>
		<pose>Unspecified</pose>
		<truncated>0</truncated>
		<difficult>0</difficult>
		<bndbox>
			<xmin>658</xmin>
			<ymin>91</ymin>
			<xmax>683</xmax>
			<ymax>115</ymax>
		</bndbox>
	</object>
	<object>
		<name>no_parking</name>
		<pose>Unspecified</pose>
		<truncated>0</truncated>
		<difficult>0</difficult>
		<bndbox>
			<xmin>655</xmin>
			<ymin>64</ymin>
			<xmax>686</xmax>
			<ymax>93</ymax>
		</bndbox>
	</object>
</annotation>
