<annotation>
	<folder>70</folder>
	<filename>FILE190902-160945F.MP4.thumb0023.jpg</filename>
	<path>/home/mi/road_sign_detection/Data/Road_signs/70/FILE190902-160945F.MP4.thumb0023.jpg</path>
	<source>
		<database>Unknown</database>
	</source>
	<size>
		<width>1920</width>
		<height>1080</height>
		<depth>3</depth>
	</size>
	<segmented>0</segmented>
	<object>
		<name>speed_limit_70</name>
		<pose>Unspecified</pose>
		<truncated>0</truncated>
		<difficult>0</difficult>
		<bndbox>
			<xmin>1758</xmin>
			<ymin>350</ymin>
			<xmax>1836</xmax>
			<ymax>436</ymax>
		</bndbox>
	</object>
	<object>
		<name>no_parking</name>
		<pose>Unspecified</pose>
		<truncated>0</truncated>
		<difficult>0</difficult>
		<bndbox>
			<xmin>1767</xmin>
			<ymin>433</ymin>
			<xmax>1851</xmax>
			<ymax>533</ymax>
		</bndbox>
	</object>
</annotation>
