<annotation>
	<folder>60</folder>
	<filename>FILE190726-161310F.MP4.thumb0032.jpg</filename>
	<path>/home/mi/road_sign_detection/Data/Road_signs/60/FILE190726-161310F.MP4.thumb0032.jpg</path>
	<source>
		<database>Unknown</database>
	</source>
	<size>
		<width>1920</width>
		<height>1080</height>
		<depth>3</depth>
	</size>
	<segmented>0</segmented>
	<object>
		<name>road_works</name>
		<pose>Unspecified</pose>
		<truncated>0</truncated>
		<difficult>0</difficult>
		<bndbox>
			<xmin>969</xmin>
			<ymin>626</ymin>
			<xmax>1000</xmax>
			<ymax>650</ymax>
		</bndbox>
	</object>
	<object>
		<name>road_works</name>
		<pose>Unspecified</pose>
		<truncated>0</truncated>
		<difficult>0</difficult>
		<bndbox>
			<xmin>597</xmin>
			<ymin>611</ymin>
			<xmax>626</xmax>
			<ymax>635</ymax>
		</bndbox>
	</object>
	<object>
		<name>speed_limit_60</name>
		<pose>Unspecified</pose>
		<truncated>0</truncated>
		<difficult>0</difficult>
		<bndbox>
			<xmin>600</xmin>
			<ymin>634</ymin>
			<xmax>625</xmax>
			<ymax>657</ymax>
		</bndbox>
	</object>
	<object>
		<name>speed_limit_60</name>
		<pose>Unspecified</pose>
		<truncated>0</truncated>
		<difficult>0</difficult>
		<bndbox>
			<xmin>970</xmin>
			<ymin>650</ymin>
			<xmax>997</xmax>
			<ymax>671</ymax>
		</bndbox>
	</object>
	<object>
		<name>no_overtaking</name>
		<pose>Unspecified</pose>
		<truncated>0</truncated>
		<difficult>0</difficult>
		<bndbox>
			<xmin>966</xmin>
			<ymin>671</ymin>
			<xmax>993</xmax>
			<ymax>696</ymax>
		</bndbox>
	</object>
</annotation>
